pysaltcorn/__init__.py
pysaltcorn/py.typed
pysaltcorn/support.py
pysaltcorn-0.3.1.dist-info/WHEEL
pysaltcorn-0.3.1.dist-info/METADATA
pysaltcorn-0.3.1.dist-info/RECORD
