Metadata-Version: 2.1
Name: pysaltcorn
Version: 0.3.1
Summary: Python library for Saltcorn API
License: MIT
Author: Michael Dubner
Author-email: pywebmail@list.ru
Requires-Python: >=3.10,<4.0
Classifier: License :: OSI Approved :: MIT License
Classifier: Programming Language :: Python :: 3
Classifier: Programming Language :: Python :: 3.10
Requires-Dist: requests (>=2.28.1,<3.0.0)
